neuro_tools/__init__.py
neuro_tools/jupyter/__init__.py
neuro_tools/jupyter/selectfile.py
neuro_tools/jupyter/xnat_form.py
neuro_tools/neuroquant/__init__.py
neuro_tools/xnat/Xnat.py
neuro_tools/xnat/__init__.py
neuro_tools/xnat/util.py
neuro_tools-0.1.1.dist-info/METADATA
neuro_tools-0.1.1.dist-info/RECORD
neuro_tools-0.1.1.dist-info/WHEEL
neuro_tools-0.1.1.dist-info/top_level.txt
